[{"name":"docs","nodes":[{"name":"rules","nodes":[{"name":"check-jsdoc-param-type.md","content":"# verify whether JSDoc param type is correct. (wrong-jsdoc-param-type)\r\n\r\n## Rule Details\r\n\r\nExamples of **incorrect** code for this rule:\r\n\r\n```js\r\nsap.ui.define(\r\n  [\"sap/m/Button\", \"sap/ui/model/json/JSONModel\"],\r\n  /*\r\n   * @param {any} oButton\r\n   * @param {object} oModel\r\n   */\r\n  function(oButton, oModel) {\r\n    // your code\r\n  }\r\n);\r\n```\r\n\r\nExamples of **correct** code for this rule:\r\n\r\n```js\r\nsap.ui.define(\r\n  [\"sap/m/Button\", \"sap/ui/model/json/JSONModel\"],\r\n  /*\r\n   * @param {sap.m.Button} oButton\r\n   * @param {sap.ui.model.json.JSONModel} oModel\r\n   */\r\n  function(oButton, oModel) {\r\n    // your code\r\n  }\r\n);\r\n```\r\n\r\n### Options\r\n\r\nThe rule is fixable\r\n"},{"name":"duplicate-jsdoc-params.md","content":"# verify whether JSDoc param type is defined (no-jsdoc-param-type)\r\n\r\n## Rule Details\r\n\r\nExamples of **incorrect** code for this rule:\r\n\r\n```js\r\nsap.ui.define(\r\n  [\"sap/m/Button\", \"sap/ui/model/json/JSONModel\"],\r\n  /*\r\n   * @param oButton\r\n   * @param {} oModel\r\n   */\r\n  function(oButton, oModel) {\r\n    // your code\r\n  }\r\n);\r\n```\r\n\r\nExamples of **correct** code for this rule:\r\n\r\n```js\r\nsap.ui.define(\r\n  [\"sap/m/Button\", \"sap/ui/model/json/JSONModel\"],\r\n  /*\r\n   * @param {sap.m.Button} oButton\r\n   * @param {sap.ui.model.json.JSONModel} oModel\r\n   */\r\n  function(oButton, oModel) {\r\n    // your code\r\n  }\r\n);\r\n```\r\n\r\n### Options\r\n\r\nThe rule is not fixable\r\n"},{"name":"no-jsdoc-param.md","content":"# verify whether JSDoc param is defined. (no-jsdoc-param)\r\n\r\n## Rule Details\r\n\r\nExamples of **incorrect** code for this rule:\r\n\r\n```js\r\nsap.ui.define(\r\n  [\"sap/m/Button\", \"sap/ui/model/json/JSONModel\"],\r\n  /*\r\n   * @param {sap.ui.model.json.JSONModel} oModel\r\n   */\r\n  function(oButton, oModel) {\r\n    // your code\r\n  }\r\n);\r\n```\r\n\r\nExamples of **correct** code for this rule:\r\n\r\n```js\r\nsap.ui.define(\r\n  [\"sap/m/Button\", \"sap/ui/model/json/JSONModel\"],\r\n  /*\r\n   * @param {sap.m.Button} oButton\r\n   * @param {sap.ui.model.json.JSONModel} oModel\r\n   */\r\n  function(oButton, oModel) {\r\n    // your code\r\n  }\r\n);\r\n```\r\n\r\n### Options\r\n\r\nThe rule is fixable\r\n"},{"name":"no-jsdoc.md","content":"# verify whether JSDoc is provided (no-jsdoc)\r\n\r\n## Rule Details\r\n\r\nExamples of **incorrect** code for this rule:\r\n\r\n```js\r\nsap.ui.define(\r\n  [\"sap/m/Button\", \"sap/ui/model/json/JSONModel\"],\r\n\r\n  function(oButton, oModel) {\r\n    // your code\r\n  }\r\n);\r\n```\r\n\r\nExamples of **correct** code for this rule:\r\n\r\n```js\r\nsap.ui.define(\r\n  [\"sap/m/Button\", \"sap/ui/model/json/JSONModel\"],\r\n  /*\r\n   * @param {sap.m.Button} oButton\r\n   * @param {sap.ui.model.json.JSONModel} oModel\r\n   */\r\n  function(oButton, oModel) {\r\n    // your code\r\n  }\r\n);\r\n```\r\n\r\n### Options\r\n\r\nThe rule is fixable\r\n"}]}]},{"name":"README.md","content":"## Overview\r\n\r\nThis is the eslint plugin for UI5 appplications. It contains a set of eslint rules and recommended ESLint configuration for static jsdoc code checks of sap.ui.define modules to be used by UI5 appplication developers.\r\n\r\n## Usage\r\n\r\nTo add this package as a dependency in your **package.json** file, do the following:\r\n\r\n1. Under the \"devDependencies\" section, add the following dependency: `\"@sap/eslint-plugin-ui5-jsdocs\": \"2.0.x\"`\r\n1. Add `.eslintrc.json` file with the following content:\r\n\r\n```json\r\n{\r\n  \"plugins\": [\"@sap/ui5-jsdocs\"],\r\n  \"extends\": \"plugin:@sap/ui5-jsdocs/recommended\"\r\n}\r\n```\r\n\r\n## List of rules\r\n\r\n| Rule                                                           | Description                                      | Recommended Severity | Fixable |\r\n| :------------------------------------------------------------- | :----------------------------------------------- | :------------------- | :------ |\r\n| [no-jsdoc](docs/rules/no-jsdoc.md)                             | There is no JSDoc provided                       | Warning              | yes     |\r\n| [no-jsdoc-param](docs/rules/no-jsdoc-param.md)                 | There is no JSDoc param defined                  | Warning              | yes     |\r\n| [check-jsdoc-param-type](docs/rules/check-jsdoc-param-type.md) | The JSDoc param type is incorrect                | Warning              | yes     |\r\n| [duplicate-jsdoc-params](docs/rules/duplicate-jsdoc-params.md) | The argument should contain only one JSDoc param | Warning              | no      |\r\n\r\n"}]